[
    {
        "id" : "1",
        "name" : "Iphone 15 Pro Max",
        "brand" : "Apple",
        "price" : "Rp. 29.999.000",
        "image" : "https://encrypted-tbn0.gstatic.com/images?q=tbn:ANd9GcTh2SiI2mH0DbHE2_gdzvT2jM9tpXEC8J1Bwg&s",
        "description" : "Layar 6.7 inci Super Retina XDR dengan ProMotion, Chip A17 Pro, Kamera utama 48MP dengan sensor-shift OIS, Kamera ultra-wide 12MP, Kamera telefoto 5x zoom optik, Perekaman video ProRes, Kapasitas baterai hingga 29 jam pemutaran video, Sistem operasi iOS 17"

    },
    {
        "id" : "2",
        "name" : "Samsung Galaxy S23 Ultra",
        "brand" : "Samsung",
        "price" : "Rp. 18.999.000",
        "image" : "https://encrypted-tbn0.gstatic.com/images?q=tbn:ANd9GcSMT1k1Ly3jOVG4yYVdWKlYFX3JahQBZE4R3Q&s",
        "description" : "Layar 6.8 inci Dynamic AMOLED 2X dengan refresh rate 120Hz, Chipset Snapdragon 8 Gen 2, Kamera utama 200MP, Kamera ultra-wide 12MP, Kamera telefoto 10MP (3x zoom optik) dan 10MP (10x zoom optik), Kapasitas baterai 5000mAh dengan pengisian cepat 45W, Sistem operasi Android 13 dengan One UI 5.1"

    },
    {
        "id" : "3",
        "name" : "Google Pixel 7 Pro",
        "brand" : "Google",
        "price" : "Rp. 14.999.000",
        "image" : "https://m.media-amazon.com/images/I/51OFxuD1GgL.jpg",
        "description" : "Layar 6.7 inci LTPO OLED dengan refresh rate hingga 120Hz, Chipset Google Tensor G2, Kamera utama 50MP, Kamera ultra-wide 12MP, Kamera telefoto 48MP (5x zoom optik), Kapasitas baterai 5000mAh dengan pengisian cepat 30W, Sistem operasi Android 13"

    },
    {
        "id" : "4",
        "name" : "OnePlus 11",
        "brand" : "OnePlus",
        "price" : "Rp. 12.999.000",
        "image" : "https://fdn2.gsmarena.com/vv/pics/oneplus/oneplus-11-1.jpg",
        "description" : "Layar 6.7 inci AMOLED dengan refresh rate 120Hz, Chipset Snapdragon 8 Gen 2, Kamera utama 50MP, Kamera ultra-wide 48MP, Kamera telefoto 32MP, Kapasitas baterai 5000mAh dengan pengisian cepat 100W, Sistem operasi Android 13 dengan OxygenOS 13"

    },
    {
        "id" : "5",
        "name" : "Xiaomi 13 Pro",
        "brand" : "Xiaomi",
        "price" : "Rp. 15.999.000",
        "image" : "https://carisinyal.com/wp-content/uploads/2022/12/Xiaomi-13-Pro_.webp",
        "description" : "Layar 6.73 inci AMOLED dengan resolusi 3200 x 1440 piksel dan refresh rate 120Hz, Chipset Snapdragon 8 Gen 2, Kamera utama 50MP, Kamera ultra-wide 50MP, Kamera telefoto 50MP (3.2x zoom optik), Kapasitas baterai 4820mAh dengan pengisian cepat 120W, Sistem operasi Android 13 dengan MIUI 14"
    },
    {
        "id" :"6",
        "name" : "Samsung Galaxy S24 Ultra",
        "brand" : "Samsung",
        "price" : "Rp. 19.999.000",
        "image" : "https://cellmart.pk/wp-content/uploads/2024/07/S24-Ultra-Yellow-cellmart.jpg",
        "description" : "Layar 6.8 inci Dynamic AMOLED 2X dengan refresh rate 120Hz, Chipset Snapdragon 8 Gen 2, Kamera utama 200MP, Kamera ultra-wide 12MP, Kamera telefoto 10MP (3x zoom optik) dan 10MP (10x zoom optik), Kapasitas baterai 5000mAh dengan pengisian cepat 45W, Sistem operasi Android 14 dengan One UI 5.1"

    },
    {
        "id" : "7",
        "name" : "Asus Rog Phone 8",
        "brand" : "Asus",
        "price" : "Rp. 14.999.000",
        "image" : "https://fdn2.gsmarena.com/vv/pics/asus/asus-rog-phone-8-1.jpg",
        "description" : "Layar 6.78 inci AMOLED dengan refresh rate 165Hz, Chipset Snapdragon 8 Gen 2, Kamera utama 50MP, Kamera ultra-wide 13MP, Kamera makro 5MP, Kapasitas baterai 6000mAh dengan pengisian cepat 65W, Sistem operasi Android 13 dengan ROG UI"

    },
    {
        "id": "8",
        "name" : "Xiaomi 14 Pro",
        "brand" : "Xiaomi",
        "price" : "Rp. 16.999.000",
        "image": "https://fdn2.gsmarena.com/vv/pics/xiaomi/xiaomi-14-pro-1.jpg",
        "description" : "Layar 6.73 inci AMOLED dengan resolusi 3200 x 1440 piksel dan refresh rate 120Hz, Chipset Snapdragon 8 Gen 2, Kamera utama 50MP, Kamera ultra-wide 50MP, Kamera telefoto 50MP (3.2x zoom optik), Kapasitas baterai 4820mAh dengan pengisian cepat 120W, Sistem operasi Android 14 dengan MIUI 14"
    },
    {
        "id" : "9",
        "name" : "Iphone 14 Pro Max",
        "brand" : "Apple",
        "price" : "Rp. 24.999.000",
        "image" : "https://hybrid.co.id/wp-content/uploads/2022/09/cec6f6731d5c6418412237424b17bf42_Apple-iPhone-14-Pro-iPhone-14-Pro-Max-space-black-220907.jpg",
        "description" : "Layar 6.7 inci Super Retina XDR dengan ProMotion, Chip A16 Bionic, Kamera utama 48MP dengan sensor-shift OIS, Kamera ultra-wide 12MP, Kamera telefoto 3x zoom optik, Perekaman video ProRes, Kapasitas baterai hingga 29 jam pemutaran video, Sistem operasi iOS 16"  
    },
    {
        "id" : "10",
        "name" : "Google Pixel 8 Pro",
        "brand" : "Google",
        "price" : "Rp. 15.999.000",
        "image" : "https://fdn2.gsmarena.com/vv/pics/google/google-pixel-8-pro-1.jpg",
        "description" : "Layar 6.7 inci LTPO OLED dengan refresh rate hingga 120Hz, Chipset Google Tensor G3, Kamera utama 50MP, Kamera ultra-wide 12MP, Kamera telefoto 48MP (5x zoom optik), Kapasitas baterai 5000mAh dengan pengisian cepat 30W, Sistem operasi Android 14"
    },
    {
        "id" : "11",
        "name" : "OnePlus 12",
        "brand" : "OnePlus",
        "price" : "Rp. 13.999.000",
        "image" : "https://fdn2.gsmarena.com/vv/pics/oneplus/oneplus-12-1.jpg",
        "description" : "Layar 6.7 inci AMOLED dengan refresh rate 120Hz, Chipset Snapdragon 8 Gen 3, Kamera utama 50MP, Kamera ultra-wide 48MP, Kamera telefoto 32MP, Kapasitas baterai 5000mAh dengan pengisian cepat 100W, Sistem operasi Android 14 dengan OxygenOS 14"
    },
    {
        "id" : "12",
        "name" : "Asus Rog Phone 9",
        "brand" : "Asus",
        "price" : "Rp. 15.999.000",
        "image" : "https://fdn2.gsmarena.com/vv/pics/asus/asus-rog-phone-9-1.jpg",
        "description" : "Layar 6.78 inci AMOLED dengan refresh rate 165Hz, Chipset Snapdragon 8 Gen 3, Kamera utama 50MP, Kamera ultra-wide 13MP, Kamera makro 5MP, Kapasitas baterai 6000mAh dengan pengisian cepat 65W, Sistem operasi Android 14 dengan ROG UI"
    }

]